[
    { 
        "label": "Администрация", 
        "id": "administration", 
        "value": 5, 
        "message": "Вы уволены!", 
        "warn": "Вы на грани увольнения!",
        "color": "blue" 
    }, { 
        "label": "Коллеги", 
        "id": "colleagues", 
        "value": 7, 
        "message": "Профсоюз добился Вашего увольнения!", 
        "warn": "Отношения в коллективе напряженные.",
        "color": "red" 
    }, { 
        "label": "Родители", 
        "id": "parents", 
        "value": 6, 
        "message": "Родители устроили скандал в школе.", 
        "warn": "Родители недовольны Вашей работой.",
        "color": "cyan" 
    }, { 
        "label": "Ученики", 
        "id": "students", 
        "value": 8, 
        "message": "Ученики устроили бунт.", 
        "warn": "Ученики жалуются на Вас.",
        "color": "yellow" 
    }, { 
        "label": "Свободное время", 
        "id": "freeTime", 
        "value": 8, 
        "message": "Вы выгорели.", 
        "warn": "Вы перерабатываете.",
        "color": "lime"
    }
]